pyqt_windows_buttons_widget/__init__.py
pyqt_windows_buttons_widget/windowsButtonsWidget.py
pyqt_windows_buttons_widget-0.0.18.dist-info/LICENSE
pyqt_windows_buttons_widget-0.0.18.dist-info/METADATA
pyqt_windows_buttons_widget-0.0.18.dist-info/WHEEL
pyqt_windows_buttons_widget-0.0.18.dist-info/top_level.txt
pyqt_windows_buttons_widget-0.0.18.dist-info/RECORD
