Metadata-Version: 2.1
Name: pyqt-windows-buttons-widget
Version: 0.0.18
Summary: PyQt Windows titlebar buttons (e.g. min/max/close button) widget
Home-page: https://github.com/yjg30737/pyqt-windows-buttons-widget.git
Author: Jung Gyu Yoon
Author-email: yjg30737@gmail.com
License: MIT
Platform: UNKNOWN
License-File: LICENSE
Requires-Dist: PyQt5 (>=5.8)
Requires-Dist: pyqt-titlebar-buttons-widget (>=0.0.1)
